PYSlots/__init__.py
PYSlots/__main__.py
PYSlots/args.py
PYSlots/original_gamemode.py
PYSlots/other_games.py
PYSlots/update.py
PYSlots/user_input_gamemode.py
PYSlots-1.3.0.dist-info/LICENSE
PYSlots-1.3.0.dist-info/METADATA
PYSlots-1.3.0.dist-info/WHEEL
PYSlots-1.3.0.dist-info/entry_points.txt
PYSlots-1.3.0.dist-info/top_level.txt
PYSlots-1.3.0.dist-info/RECORD
