Metadata-Version: 2.1
Name: PYSlots
Version: 1.3.0
Summary: A fun terminal Python slots game!
Home-page: https://github.com/Lukas-Batema/pyslots
Author: Lukas-Batema
Author-email: lukasbatema@gmail.com
License: UNKNOWN
Project-URL: Bug Tracker, https://github.com/Lukas-Batema/pyslots/issues
Keywords: python,py,slots,pyslots
Platform: UNKNOWN
Classifier: Programming Language :: Python :: 3
Classifier: License :: OSI Approved :: MIT License
Classifier: Operating System :: OS Independent
Requires-Python: >=3.6
License-File: LICENSE
